smqtk_iqr/__init__.py
smqtk_iqr/iqr/__init__.py
smqtk_iqr/iqr/iqr_controller.py
smqtk_iqr/iqr/iqr_session.py
smqtk_iqr/py.typed
smqtk_iqr/utils/__init__.py
smqtk_iqr/utils/cli.py
smqtk_iqr/utils/database_info.py
smqtk_iqr/utils/iqrTrainClassifier.py
smqtk_iqr/utils/iqr_app_model_generation.py
smqtk_iqr/utils/mimetype.py
smqtk_iqr/utils/mongo_sessions.py
smqtk_iqr/utils/preview_cache.py
smqtk_iqr/utils/runApplication.py
smqtk_iqr/utils/url.py
smqtk_iqr/utils/video.py
smqtk_iqr/utils/web.py
smqtk_iqr/web/__init__.py
smqtk_iqr/web/iqr_service/__init__.py
smqtk_iqr/web/iqr_service/api.rst
smqtk_iqr/web/iqr_service/iqr_server.py
smqtk_iqr/web/iqr_service/use_case_example.rst
smqtk_iqr/web/search_app/README.rst
smqtk_iqr/web/search_app/__init__.py
smqtk_iqr/web/search_app/modules/__init__.py
smqtk_iqr/web/search_app/modules/file_upload/FileUploadMod.py
smqtk_iqr/web/search_app/modules/file_upload/__init__.py
smqtk_iqr/web/search_app/modules/file_upload/static/css/smqtk_upload.css
smqtk_iqr/web/search_app/modules/file_upload/static/js/flow.js
smqtk_iqr/web/search_app/modules/file_upload/static/js/flow.min.js
smqtk_iqr/web/search_app/modules/file_upload/static/js/smqtk_upload.js
smqtk_iqr/web/search_app/modules/iqr/__init__.py
smqtk_iqr/web/search_app/modules/iqr/iqr_search.py
smqtk_iqr/web/search_app/modules/iqr/static/css/smqtk.iqr.css
smqtk_iqr/web/search_app/modules/iqr/static/img/carbon-rejected.png
smqtk_iqr/web/search_app/modules/iqr/static/img/carbon-rejected_on.png
smqtk_iqr/web/search_app/modules/iqr/static/img/carbon-verified.png
smqtk_iqr/web/search_app/modules/iqr/static/img/carbon-verified_on.png
smqtk_iqr/web/search_app/modules/iqr/static/img/explicit_marker_off.png
smqtk_iqr/web/search_app/modules/iqr/static/img/explicit_marker_on.png
smqtk_iqr/web/search_app/modules/iqr/static/img/explicit_overlay.png
smqtk_iqr/web/search_app/modules/iqr/static/img/loading.gif
smqtk_iqr/web/search_app/modules/iqr/static/js/FileSaver.LICENSE.md
smqtk_iqr-0.15.1.dist-info/entry_points.txt
smqtk_iqr-0.15.1.dist-info/LICENSE.txt
smqtk_iqr-0.15.1.dist-info/WHEEL
smqtk_iqr-0.15.1.dist-info/METADATA
smqtk_iqr-0.15.1.dist-info/RECORD
