Metadata-Version: 2.1
Name: smqtk-iqr
Version: 0.15.1
Summary: IQR datastructures and web interface
Home-page: https://github.com/Kitware/SMQTK-IQR
License: BSD-3-Clause
Author: Kitware, Inc.
Author-email: smqtk-developers@kitware.com
Requires-Python: >=3.6,<4.0
Classifier: License :: OSI Approved :: BSD License
Classifier: Programming Language :: Python :: 3
Classifier: Programming Language :: Python :: 3.6
Classifier: Programming Language :: Python :: 3.7
Classifier: Programming Language :: Python :: 3.8
Classifier: Programming Language :: Python :: 3.9
Requires-Dist: Flask (>=2.0.1,<3.0.0)
Requires-Dist: Flask-BasicAuth (>=0.2.0,<0.3.0)
Requires-Dist: Flask-Cors (>=3.0.10,<4.0.0)
Requires-Dist: Pillow (>=8.3.2,<9.0.0)
Requires-Dist: imageio (>=2.9.0,<3.0.0)
Requires-Dist: pymongo (>=3.12.0,<4.0.0)
Requires-Dist: smqtk-classifier (>=0.18.0)
Requires-Dist: smqtk-core (>=0.18)
Requires-Dist: smqtk-dataprovider (>=0.16.0)
Requires-Dist: smqtk-descriptors (>=0.18)
Requires-Dist: smqtk-indexing (>=0.17.0)
Requires-Dist: smqtk-relevancy (>=0.16.0)
Project-URL: Documentation, https://smqtk-iqr.readthedocs.io/
Project-URL: Repository, https://github.com/Kitware/SMQTK-IQR
